EasyFlowQ/__init__.py
EasyFlowQ/dialog_DrvedParam.py
EasyFlowQ/localSettings.default.json
EasyFlowQ/start.py
EasyFlowQ/window_About.py
EasyFlowQ/window_Comp.py
EasyFlowQ/window_DrvedParamEdit.py
EasyFlowQ/window_EditStain.py
EasyFlowQ/window_Main.py
EasyFlowQ/window_RenameCF.py
EasyFlowQ/window_RenameMap.py
EasyFlowQ/window_Settings.py
EasyFlowQ/window_Stats.py
EasyFlowQ/wizard_Comp.py
EasyFlowQ/FlowCal/README.md
EasyFlowQ/FlowCal/__init__.py
EasyFlowQ/FlowCal/excel_ui.py
EasyFlowQ/FlowCal/gate.py
EasyFlowQ/FlowCal/io.py
EasyFlowQ/FlowCal/mef.py
EasyFlowQ/FlowCal/plot.py
EasyFlowQ/FlowCal/stats.py
EasyFlowQ/FlowCal/transform.py
EasyFlowQ/FlowCal/ReadmeLicense/README.rst
EasyFlowQ/FlowCal/ReadmeLicense/license.txt
EasyFlowQ/backend/__init__.py
EasyFlowQ/backend/comp.py
EasyFlowQ/backend/dataIO.py
EasyFlowQ/backend/efio.py
EasyFlowQ/backend/gates.py
EasyFlowQ/backend/plotWidgets.py
EasyFlowQ/backend/qtModels.py
EasyFlowQ/backend/utils.py
EasyFlowQ/uiDesigns/AboutWindow.ui
EasyFlowQ/uiDesigns/CompWindow.ui
EasyFlowQ/uiDesigns/CompWizard.ui
EasyFlowQ/uiDesigns/CompWizard_SmplAssignBox.ui
EasyFlowQ/uiDesigns/DrvedParamEditWindow.ui
EasyFlowQ/uiDesigns/DrvedParamWindow.ui
EasyFlowQ/uiDesigns/EditStainWindow.ui
EasyFlowQ/uiDesigns/MainWindow.ui
EasyFlowQ/uiDesigns/MainWindow_FigOptions.py
EasyFlowQ/uiDesigns/MainWindow_FigOptions.ui
EasyFlowQ/uiDesigns/MainWindow_SmplSect.py
EasyFlowQ/uiDesigns/MainWindow_SmplSect.ui
EasyFlowQ/uiDesigns/RenameWindow_CF.ui
EasyFlowQ/uiDesigns/RenameWindow_Map.ui
EasyFlowQ/uiDesigns/SettingsWindow.ui
EasyFlowQ/uiDesigns/StatWindow.ui
EasyFlowQ/uiDesigns/__init__.py
EasyFlowQ/uiDesigns/resource/PelatteIcon2.png
easyflowq-1.7.1.dist-info/METADATA
easyflowq-1.7.1.dist-info/WHEEL
easyflowq-1.7.1.dist-info/entry_points.txt
easyflowq-1.7.1.dist-info/licenses/LICENSE
easyflowq-1.7.1.dist-info/RECORD
