Metadata-Version: 2.4
Name: EasyFlowQ
Version: 1.7.1
Summary: User-friendly flow cytometry analyzer with (GUI)
Project-URL: Homepage, https://github.com/ym3141/EasyFlowQ
Project-URL: Issues, https://github.com/ym3141/EasyFlowQ/issues
Author-email: Yitong Ma <yitongma7@gmail.com>
License-File: LICENSE
Classifier: License :: OSI Approved :: MIT License
Classifier: Operating System :: OS Independent
Classifier: Programming Language :: Python :: 3
Requires-Python: >=3.7
Requires-Dist: matplotlib>=3.5
Requires-Dist: numpy>=1.21
Requires-Dist: openpyxl
Requires-Dist: pandas>=2.0
Requires-Dist: pyside6>=6.7
Requires-Dist: scipy>=1.7
Requires-Dist: seaborn
Requires-Dist: sympy>=1.7
Requires-Dist: xlsxwriter
